pystrometry/__init__.py
pystrometry/_astropy_init.py
pystrometry/gaia_astrometry.py
pystrometry/pyscamp.py
pystrometry/pystrometry.py
pystrometry/version.py
pystrometry/data/README.rst
pystrometry/example_subpkg/__init__.py
pystrometry/example_subpkg/setup_package.py
pystrometry/example_subpkg/tests/__init__.py
pystrometry/extern/__init__.py
pystrometry/tests/__init__.py
pystrometry/tests/coveragerc
pystrometry/tests/setup_package.py
pystrometry/tests/test_du437_tools.py
pystrometry/tests/test_pystrometry.py
pystrometry/utils/__init__.py
pystrometry/utils/acceleration.py
pystrometry/utils/archives.py
pystrometry/utils/du437_tools.py
pystrometry/utils/mcmc_helpers.py
pystrometry/utils/tests/__init__.py
pystrometry/utils/tests/test_archives.py
pystrometry-0.6.1.dist-info/LICENSE.rst
pystrometry-0.6.1.dist-info/METADATA
pystrometry-0.6.1.dist-info/WHEEL
pystrometry-0.6.1.dist-info/entry_points.txt
pystrometry-0.6.1.dist-info/top_level.txt
pystrometry-0.6.1.dist-info/RECORD
