Metadata-Version: 2.1
Name: pystrometry
Version: 0.6.1
Summary: Support for astrometry timeseries analysis
Home-page: https://github.com/Johannes-Sahlmann/pystrometry
Author: Johannes Sahlmann
Author-email: jsahlmann@sciops.esa.int
License: BSD 3-Clause
Requires-Python: >=3.7
License-File: LICENSE.rst
Requires-Dist: astropy
Requires-Dist: linearfit >=1.0.2
Requires-Dist: matplotlib
Requires-Dist: scipy
Requires-Dist: astroquery
Requires-Dist: sympy
Requires-Dist: pandas
Requires-Dist: pyarrow
